pistachio/__init__.py
pistachio/models.py
pistachio/transfer_matrix.py
pistachio/data/__init__.py
pistachio/data/refractive_index_data/__init__.py
pistachio/default/__init__.py
pistachio_tm-0.10.11.dist-info/LICENSE
pistachio_tm-0.10.11.dist-info/METADATA
pistachio_tm-0.10.11.dist-info/WHEEL
pistachio_tm-0.10.11.dist-info/top_level.txt
pistachio_tm-0.10.11.dist-info/RECORD
